Inde_Abbre/__init__.py
Inde_Abbre/output_2.json
Inde_Abbre-0.4.dist-info/LICENSE
Inde_Abbre-0.4.dist-info/METADATA
Inde_Abbre-0.4.dist-info/WHEEL
Inde_Abbre-0.4.dist-info/top_level.txt
Inde_Abbre-0.4.dist-info/RECORD
