Metadata-Version: 2.1
Name: Inde-Abbre
Version: 0.4
Summary: A Library that is used to retrieve the INDIAN Abbreviations
Home-page: UNKNOWN
Author: Richard Alphone
Author-email: richardriche96@gmail.com
License: UNKNOWN
Platform: UNKNOWN
Classifier: Operating System :: Microsoft :: Windows :: Windows 10
Classifier: License :: OSI Approved :: MIT License
Classifier: Programming Language :: Python :: 3
License-File: LICENSE
Requires-Dist: pandas
Requires-Dist: json
Requires-Dist: os
